aiohappyeyeballs/__init__.py
aiohappyeyeballs/_staggered.py
aiohappyeyeballs/impl.py
aiohappyeyeballs/py.typed
aiohappyeyeballs/types.py
aiohappyeyeballs/utils.py
aiohappyeyeballs-2.4.7.dist-info/LICENSE
aiohappyeyeballs-2.4.7.dist-info/METADATA
aiohappyeyeballs-2.4.7.dist-info/WHEEL
aiohappyeyeballs-2.4.7.dist-info/RECORD
