Metadata-Version: 2.3
Name: aiohappyeyeballs
Version: 2.4.7
Summary: Happy Eyeballs for asyncio
License: PSF-2.0
Author: J. Nick Koston
Author-email: nick@koston.org
Requires-Python: >=3.9
Classifier: Development Status :: 5 - Production/Stable
Classifier: Intended Audience :: Developers
Classifier: Natural Language :: English
Classifier: Operating System :: OS Independent
Classifier: Topic :: Software Development :: Libraries
Classifier: Programming Language :: Python :: 3
Classifier: Programming Language :: Python :: 3.9
Classifier: Programming Language :: Python :: 3.10
Classifier: Programming Language :: Python :: 3.11
Classifier: Programming Language :: Python :: 3.12
Classifier: Programming Language :: Python :: 3.13
Classifier: License :: OSI Approved :: Python Software Foundation License
Project-URL: Bug Tracker, https://github.com/aio-libs/aiohappyeyeballs/issues
Project-URL: Changelog, https://github.com/aio-libs/aiohappyeyeballs/blob/main/CHANGELOG.md
Project-URL: Documentation, https://aiohappyeyeballs.readthedocs.io
Project-URL: Repository, https://github.com/aio-libs/aiohappyeyeballs
